LICENSE
MANIFEST.in
README.md
setup.json
setup.py
rlgym.egg-info/PKG-INFO
rlgym.egg-info/SOURCES.txt
rlgym.egg-info/dependency_links.txt
rlgym.egg-info/requires.txt
rlgym.egg-info/top_level.txt
rlgym/version/__init__.py
rlgym/version/version.py